wordlette/__init__.py
wordlette/base_exceptions.py
wordlette/cms/__init__.py
wordlette/cms/app.py
wordlette/cms/app_bootstrap.py
wordlette/cms/cli.py
wordlette/cms/exceptions.py
wordlette/cms/extensions/__init__.py
wordlette/cms/extensions/error_pages.py
wordlette/cms/forms.py
wordlette/cms/resources/themes/default/errors/404.html
wordlette/cms/resources/themes/default/errors/default.html
wordlette/cms/resources/themes/default/foot.html
wordlette/cms/resources/themes/default/form.html
wordlette/cms/resources/themes/default/head.html
wordlette/cms/resources/themes/default/index.html
wordlette/cms/resources/themes/setup/form.html
wordlette/cms/resources/themes/setup/index.html
wordlette/cms/resources/themes/setup/setup-complete.html
wordlette/cms/resources/themes/setup/setup-page.html
wordlette/cms/states/__init__.py
wordlette/cms/states/serving.py
wordlette/cms/states/setup/__init__.py
wordlette/cms/states/setup/enums.py
wordlette/cms/states/setup/route_types.py
wordlette/cms/states/setup/routes/__init__.py
wordlette/cms/states/setup/routes/complete.py
wordlette/cms/states/setup/routes/configure_database.py
wordlette/cms/states/setup/routes/create_settings.py
wordlette/cms/states/setup/routes/index.py
wordlette/cms/states/setup/routes/launch.py
wordlette/cms/states/setup/states.py
wordlette/cms/themes/__init__.py
wordlette/cms/themes/template_loaders.py
wordlette/cms/themes/templates.py
wordlette/cms/themes/theme_managers.py
wordlette/configs/__init__.py
wordlette/configs/exceptions.py
wordlette/configs/extensions.py
wordlette/configs/handlers.py
wordlette/configs/json_handlers.py
wordlette/configs/managers.py
wordlette/configs/models.py
wordlette/configs/toml_handlers.py
wordlette/configs/yaml_handlers.py
wordlette/core/__init__.py
wordlette/core/app.py
wordlette/core/events.py
wordlette/core/exceptions.py
wordlette/core/setup_routes.py
wordlette/databases/__init__.py
wordlette/databases/controllers.py
wordlette/databases/driver_sqlite.py
wordlette-0.1.0a11.dist-info/LICENSE
wordlette-0.1.0a11.dist-info/METADATA
wordlette-0.1.0a11.dist-info/WHEEL
wordlette-0.1.0a11.dist-info/entry_points.txt
wordlette-0.1.0a11.dist-info/RECORD
